LICENSE
README.md
setup.cfg
setup.py
HiCShuffle/__init__.py
HiCShuffle/commands.py
HiCShuffle/version.py
HiCShuffle.egg-info/PKG-INFO
HiCShuffle.egg-info/SOURCES.txt
HiCShuffle.egg-info/dependency_links.txt
HiCShuffle.egg-info/requires.txt
HiCShuffle.egg-info/top_level.txt
bin/hicshuffle