Metadata-Version: 2.1
Name: HiCShuffle
Version: 1.1.2
Summary: FASTQ Shuffling Tool For Sanity Check in Hi-C Differential Contact Analysis
Home-page: https://github.com/hanjunlee21/HiCShuffle
Author: Hanjun Lee
Author-email: hanjun@mit.edu
License: MIT
Download-URL: https://github.com/hanjunlee21/HiCShuffle/archive/refs/tags/v.1.1.2.tar.gz
Keywords: hi-c,qc
Platform: UNKNOWN
Classifier: Development Status :: 5 - Production/Stable
Classifier: Intended Audience :: Science/Research
Classifier: Topic :: Scientific/Engineering :: Bio-Informatics
Classifier: License :: OSI Approved :: MIT License
Classifier: Programming Language :: Python :: 3
Classifier: Programming Language :: Python :: 3.0
Classifier: Programming Language :: Python :: 3.1
Classifier: Programming Language :: Python :: 3.2
Classifier: Programming Language :: Python :: 3.3
Classifier: Programming Language :: Python :: 3.4
Classifier: Programming Language :: Python :: 3.5
Classifier: Programming Language :: Python :: 3.6
Classifier: Programming Language :: Awk
Classifier: Programming Language :: Unix Shell
